setup.py
senstream/__init__.py
senstream/alert_manager.py
senstream/lab_streamer.py
senstream/report_manager.py
senstream/resensys.py
senstream/senimax.py
senstream/senscope.py
senstream/senspot.py
senstream/stream_builder.py
senstreamlib.egg-info/PKG-INFO
senstreamlib.egg-info/SOURCES.txt
senstreamlib.egg-info/dependency_links.txt
senstreamlib.egg-info/top_level.txt