Metadata-Version: 1.0
Name: senstreamlib
Version: 1.0
Summary: Resensys Python SDK for building SenSpot Data Pipelines and Time Series Analysis Tools.
Home-page: UNKNOWN
Author: Tom Wade
Author-email: thomas.wade@resensys.com
License: UNKNOWN
Platform: UNKNOWN
